kin_base/__init__.py
kin_base/asset.py
kin_base/base58.py
kin_base/builder.py
kin_base/exceptions.py
kin_base/horizon.py
kin_base/keypair.py
kin_base/memo.py
kin_base/network.py
kin_base/operation.py
kin_base/purecrc16.py
kin_base/transaction.py
kin_base/transaction_envelope.py
kin_base/utils.py
kin_base/version.py
kin_base/stellarxdr/StellarXDR_const.py
kin_base/stellarxdr/StellarXDR_pack.py
kin_base/stellarxdr/StellarXDR_type.py
kin_base/stellarxdr/__init__.py
kin_base/stellarxdr/updatexdr.py
kin_base/stellarxdr/xdrgen.py
kin_base/wordlist/chinese.txt
tests/__init__.py
tests/conftest.py
tests/test_asset.py
tests/test_builder.py
tests/test_envelope.py
tests/test_horizon.py
tests/test_keypair.py
tests/test_memo.py
tests/test_operation.py
tests/test_transaction.py
tests/test_utils.py
kin_base-1.4.1.dist-info/LICENSE
kin_base-1.4.1.dist-info/METADATA
kin_base-1.4.1.dist-info/WHEEL
kin_base-1.4.1.dist-info/top_level.txt
kin_base-1.4.1.dist-info/RECORD
